spyrk/__about__.py
spyrk/__init__.py
spyrk/spark_cloud.py
spyrk-0.0.4.dist-info/DESCRIPTION.rst
spyrk-0.0.4.dist-info/METADATA
spyrk-0.0.4.dist-info/RECORD
spyrk-0.0.4.dist-info/WHEEL
spyrk-0.0.4.dist-info/metadata.json
spyrk-0.0.4.dist-info/top_level.txt
