Metadata-Version: 1.1
Name: spyrk
Version: 0.0.4
Summary: Python module for Spark devices
Home-page: https://github.com/Alidron/spyrk
Author: Axel Voitier
Author-email: axel.voitier@gmail.com
License: LGPLv3
Keywords: spark cloud core arduino api embedded
Platform: UNKNOWN
Classifier: Development Status :: 3 - Alpha
Classifier: Intended Audience :: Developers
Classifier: Topic :: Home Automation
Classifier: Topic :: Software Development :: Embedded Systems
Classifier: License :: OSI Approved :: GNU Lesser General Public License v3 (LGPLv3)
Classifier: Programming Language :: Python :: 2
Classifier: Programming Language :: Python :: 2.6
Classifier: Programming Language :: Python :: 2.7
Classifier: Programming Language :: Python :: 3
Classifier: Programming Language :: Python :: 3.2
Classifier: Programming Language :: Python :: 3.3
Classifier: Programming Language :: Python :: 3.4
